weatherincity/__init__.py
weatherincity/weatherincity.py
weatherincity-1.0.1.dist-info/LICENSE.txt
weatherincity-1.0.1.dist-info/METADATA
weatherincity-1.0.1.dist-info/WHEEL
weatherincity-1.0.1.dist-info/top_level.txt
weatherincity-1.0.1.dist-info/RECORD
